{"pages":["FiraSans-SemiBold.png"],"chars":[{"id":106,"width":21,"height":53,"xoffset":0,"yoffset":-33.726,"xadvance":11.802000000000001,"chnl":15,"x":0,"y":0,"page":0},{"id":40,"width":23,"height":52,"xoffset":0,"yoffset":-35.910000000000004,"xadvance":13.608,"chnl":15,"x":0,"y":55,"page":0},{"id":41,"width":23,"height":52,"xoffset":0,"yoffset":-35.910000000000004,"xadvance":13.608,"chnl":15,"x":0,"y":109,"page":0},{"id":36,"width":32,"height":52,"xoffset":0,"yoffset":-34.818000000000005,"xadvance":22.89,"chnl":15,"x":0,"y":163,"page":0},{"id":125,"width":23,"height":51,"xoffset":0,"yoffset":-35.238,"xadvance":13.566,"chnl":15,"x":0,"y":217,"page":0},{"id":123,"width":22,"height":51,"xoffset":0,"yoffset":-35.238,"xadvance":13.566,"chnl":15,"x":0,"y":270,"page":0},{"id":64,"width":51,"height":49,"xoffset":0,"yoffset":-29.736,"xadvance":42.84,"chnl":15,"x":0,"y":323,"page":0},{"id":93,"width":22,"height":50,"xoffset":0,"yoffset":-34.482,"xadvance":13.566,"chnl":15,"x":0,"y":374,"page":0},{"id":91,"width":22,"height":50,"xoffset":0,"yoffset":-34.482,"xadvance":13.566,"chnl":15,"x":0,"y":426,"page":0},{"id":47,"width":28,"height":49,"xoffset":0,"yoffset":-34.188,"xadvance":21.84,"chnl":15,"x":24,"y":426,"page":0},{"id":92,"width":28,"height":49,"xoffset":0,"yoffset":-34.188,"xadvance":21.84,"chnl":15,"x":54,"y":426,"page":0},{"id":124,"width":21,"height":48,"xoffset":0,"yoffset":-33.978,"xadvance":16.086000000000002,"chnl":15,"x":84,"y":426,"page":0},{"id":74,"width":21,"height":46,"xoffset":0,"yoffset":-29.064,"xadvance":13.188,"chnl":15,"x":107,"y":426,"page":0},{"id":94,"width":32,"height":45,"xoffset":0,"yoffset":-35.406,"xadvance":23.268,"chnl":15,"x":130,"y":426,"page":0},{"id":103,"width":33,"height":45,"xoffset":0,"yoffset":-25.62,"xadvance":22.848000000000003,"chnl":15,"x":164,"y":426,"page":0},{"id":87,"width":45,"height":39,"xoffset":0,"yoffset":-29.064,"xadvance":35.364000000000004,"chnl":15,"x":199,"y":426,"page":0},{"id":81,"width":39,"height":45,"xoffset":0,"yoffset":-29.736,"xadvance":29.022000000000002,"chnl":15,"x":24,"y":374,"page":0},{"id":96,"width":23,"height":45,"xoffset":0,"yoffset":-34.734,"xadvance":13.860000000000001,"chnl":15,"x":65,"y":374,"page":0},{"id":105,"width":20,"height":44,"xoffset":0,"yoffset":-33.726,"xadvance":11.844000000000001,"chnl":15,"x":90,"y":374,"page":0},{"id":37,"width":44,"height":42,"xoffset":0,"yoffset":-30.156000000000002,"xadvance":35.742000000000004,"chnl":15,"x":112,"y":374,"page":0},{"id":109,"width":43,"height":33,"xoffset":0,"yoffset":-22.932000000000002,"xadvance":35.616,"chnl":15,"x":0,"y":478,"page":0},{"id":107,"width":33,"height":42,"xoffset":0,"yoffset":-31.794,"xadvance":22.764000000000003,"chnl":15,"x":158,"y":374,"page":0},{"id":104,"width":32,"height":42,"xoffset":0,"yoffset":-31.752000000000002,"xadvance":24.318,"chnl":15,"x":193,"y":374,"page":0},{"id":112,"width":33,"height":42,"xoffset":0,"yoffset":-22.932000000000002,"xadvance":25.032,"chnl":15,"x":227,"y":374,"page":0},{"id":100,"width":32,"height":42,"xoffset":0,"yoffset":-31.794,"xadvance":25.158,"chnl":15,"x":262,"y":374,"page":0},{"id":113,"width":32,"height":42,"xoffset":0,"yoffset":-22.932000000000002,"xadvance":25.158,"chnl":15,"x":296,"y":374,"page":0},{"id":108,"width":22,"height":42,"xoffset":0,"yoffset":-31.794,"xadvance":12.432,"chnl":15,"x":330,"y":374,"page":0},{"id":98,"width":33,"height":42,"xoffset":0,"yoffset":-31.794,"xadvance":25.032,"chnl":15,"x":354,"y":374,"page":0},{"id":121,"width":32,"height":42,"xoffset":0,"yoffset":-22.26,"xadvance":21.504,"chnl":15,"x":389,"y":374,"page":0},{"id":102,"width":28,"height":42,"xoffset":0,"yoffset":-31.794,"xadvance":14.742,"chnl":15,"x":423,"y":374,"page":0},{"id":38,"width":41,"height":40,"xoffset":0,"yoffset":-29.736,"xadvance":31.626,"chnl":15,"x":453,"y":374,"page":0},{"id":42,"width":28,"height":41,"xoffset":0,"yoffset":-31.122000000000003,"xadvance":18.774,"chnl":15,"x":53,"y":323,"page":0},{"id":119,"width":41,"height":32,"xoffset":0,"yoffset":-22.26,"xadvance":31.122000000000003,"chnl":15,"x":45,"y":478,"page":0},{"id":77,"width":41,"height":39,"xoffset":0,"yoffset":-29.064,"xadvance":32.928000000000004,"chnl":15,"x":246,"y":426,"page":0},{"id":48,"width":33,"height":40,"xoffset":0,"yoffset":-28.854000000000003,"xadvance":24.318,"chnl":15,"x":83,"y":323,"page":0},{"id":67,"width":34,"height":40,"xoffset":0,"yoffset":-29.736,"xadvance":23.982000000000003,"chnl":15,"x":118,"y":323,"page":0},{"id":71,"width":35,"height":40,"xoffset":0,"yoffset":-29.736,"xadvance":26.922,"chnl":15,"x":154,"y":323,"page":0},{"id":57,"width":32,"height":40,"xoffset":0,"yoffset":-28.854000000000003,"xadvance":23.184,"chnl":15,"x":191,"y":323,"page":0},{"id":63,"width":29,"height":40,"xoffset":0,"yoffset":-29.736,"xadvance":19.992,"chnl":15,"x":225,"y":323,"page":0},{"id":33,"width":19,"height":40,"xoffset":0,"yoffset":-29.064,"xadvance":10.122,"chnl":15,"x":256,"y":323,"page":0},{"id":56,"width":33,"height":40,"xoffset":0,"yoffset":-28.854000000000003,"xadvance":24.108,"chnl":15,"x":277,"y":323,"page":0},{"id":83,"width":33,"height":40,"xoffset":0,"yoffset":-29.736,"xadvance":23.73,"chnl":15,"x":312,"y":323,"page":0},{"id":85,"width":35,"height":40,"xoffset":0,"yoffset":-29.064,"xadvance":27.468,"chnl":15,"x":347,"y":323,"page":0},{"id":79,"width":37,"height":40,"xoffset":0,"yoffset":-29.736,"xadvance":29.022000000000002,"chnl":15,"x":384,"y":323,"page":0},{"id":51,"width":30,"height":40,"xoffset":0,"yoffset":-28.854000000000003,"xadvance":21.630000000000003,"chnl":15,"x":423,"y":323,"page":0},{"id":54,"width":32,"height":40,"xoffset":0,"yoffset":-28.854000000000003,"xadvance":23.352,"chnl":15,"x":455,"y":323,"page":0},{"id":53,"width":31,"height":39,"xoffset":0,"yoffset":-28.308000000000003,"xadvance":22.134,"chnl":15,"x":289,"y":426,"page":0},{"id":80,"width":34,"height":39,"xoffset":0,"yoffset":-29.064,"xadvance":24.990000000000002,"chnl":15,"x":322,"y":426,"page":0},{"id":78,"width":35,"height":39,"xoffset":0,"yoffset":-29.064,"xadvance":28.056,"chnl":15,"x":358,"y":426,"page":0},{"id":82,"width":36,"height":39,"xoffset":0,"yoffset":-29.064,"xadvance":25.788,"chnl":15,"x":395,"y":426,"page":0},{"id":55,"width":29,"height":39,"xoffset":0,"yoffset":-28.308000000000003,"xadvance":19.404,"chnl":15,"x":433,"y":426,"page":0},{"id":84,"width":32,"height":39,"xoffset":0,"yoffset":-29.064,"xadvance":22.428,"chnl":15,"x":464,"y":426,"page":0},{"id":116,"width":26,"height":39,"xoffset":0,"yoffset":-27.846,"xadvance":15.96,"chnl":15,"x":24,"y":270,"page":0},{"id":86,"width":35,"height":39,"xoffset":0,"yoffset":-29.064,"xadvance":23.814,"chnl":15,"x":52,"y":270,"page":0},{"id":65,"width":35,"height":39,"xoffset":0,"yoffset":-29.064,"xadvance":24.612000000000002,"chnl":15,"x":89,"y":270,"page":0},{"id":88,"width":34,"height":39,"xoffset":0,"yoffset":-29.064,"xadvance":23.982000000000003,"chnl":15,"x":126,"y":270,"page":0},{"id":89,"width":35,"height":39,"xoffset":0,"yoffset":-29.064,"xadvance":24.486,"chnl":15,"x":162,"y":270,"page":0},{"id":90,"width":31,"height":39,"xoffset":0,"yoffset":-29.064,"xadvance":22.638,"chnl":15,"x":199,"y":270,"page":0},{"id":66,"width":35,"height":39,"xoffset":0,"yoffset":-29.064,"xadvance":25.830000000000002,"chnl":15,"x":232,"y":270,"page":0},{"id":50,"width":30,"height":39,"xoffset":0,"yoffset":-28.854000000000003,"xadvance":21.504,"chnl":15,"x":269,"y":270,"page":0},{"id":68,"width":36,"height":39,"xoffset":0,"yoffset":-29.064,"xadvance":27.3,"chnl":15,"x":301,"y":270,"page":0},{"id":69,"width":30,"height":39,"xoffset":0,"yoffset":-29.064,"xadvance":22.176000000000002,"chnl":15,"x":339,"y":270,"page":0},{"id":70,"width":30,"height":39,"xoffset":0,"yoffset":-29.064,"xadvance":20.496000000000002,"chnl":15,"x":371,"y":270,"page":0},{"id":39,"width":18,"height":39,"xoffset":0,"yoffset":-29.064,"xadvance":9.828000000000001,"chnl":15,"x":489,"y":323,"page":0},{"id":72,"width":35,"height":39,"xoffset":0,"yoffset":-29.064,"xadvance":28.098000000000003,"chnl":15,"x":403,"y":270,"page":0},{"id":73,"width":19,"height":39,"xoffset":0,"yoffset":-29.064,"xadvance":12.348,"chnl":15,"x":440,"y":270,"page":0},{"id":59,"width":19,"height":39,"xoffset":0,"yoffset":-21.252000000000002,"xadvance":10.08,"chnl":15,"x":461,"y":270,"page":0},{"id":75,"width":37,"height":39,"xoffset":0,"yoffset":-29.064,"xadvance":26.124000000000002,"chnl":15,"x":25,"y":217,"page":0},{"id":76,"width":31,"height":39,"xoffset":0,"yoffset":-29.064,"xadvance":21.378,"chnl":15,"x":64,"y":217,"page":0},{"id":52,"width":32,"height":39,"xoffset":0,"yoffset":-28.938000000000002,"xadvance":23.394000000000002,"chnl":15,"x":97,"y":217,"page":0},{"id":34,"width":26,"height":39,"xoffset":0,"yoffset":-29.064,"xadvance":18.060000000000002,"chnl":15,"x":482,"y":270,"page":0},{"id":35,"width":32,"height":38,"xoffset":0,"yoffset":-28.308000000000003,"xadvance":22.974,"chnl":15,"x":131,"y":217,"page":0},{"id":49,"width":25,"height":38,"xoffset":0,"yoffset":-28.308000000000003,"xadvance":19.152,"chnl":15,"x":165,"y":217,"page":0},{"id":60,"width":30,"height":34,"xoffset":0,"yoffset":-23.94,"xadvance":21.588,"chnl":15,"x":192,"y":217,"page":0},{"id":62,"width":30,"height":34,"xoffset":0,"yoffset":-23.94,"xadvance":21.588,"chnl":15,"x":224,"y":217,"page":0},{"id":101,"width":32,"height":34,"xoffset":0,"yoffset":-22.932000000000002,"xadvance":23.142000000000003,"chnl":15,"x":256,"y":217,"page":0},{"id":111,"width":33,"height":34,"xoffset":0,"yoffset":-22.932000000000002,"xadvance":24.528000000000002,"chnl":15,"x":290,"y":217,"page":0},{"id":97,"width":32,"height":34,"xoffset":0,"yoffset":-22.932000000000002,"xadvance":22.974,"chnl":15,"x":325,"y":217,"page":0},{"id":99,"width":30,"height":34,"xoffset":0,"yoffset":-22.932000000000002,"xadvance":20.076,"chnl":15,"x":359,"y":217,"page":0},{"id":115,"width":29,"height":34,"xoffset":0,"yoffset":-22.932000000000002,"xadvance":20.118000000000002,"chnl":15,"x":391,"y":217,"page":0},{"id":114,"width":27,"height":33,"xoffset":0,"yoffset":-22.89,"xadvance":16.674,"chnl":15,"x":422,"y":217,"page":0},{"id":110,"width":32,"height":33,"xoffset":0,"yoffset":-22.932000000000002,"xadvance":24.318,"chnl":15,"x":451,"y":217,"page":0},{"id":117,"width":31,"height":33,"xoffset":0,"yoffset":-22.26,"xadvance":24.108,"chnl":15,"x":34,"y":163,"page":0},{"id":43,"width":30,"height":33,"xoffset":0,"yoffset":-22.764000000000003,"xadvance":21.966,"chnl":15,"x":67,"y":163,"page":0},{"id":120,"width":32,"height":32,"xoffset":0,"yoffset":-22.26,"xadvance":21.21,"chnl":15,"x":88,"y":478,"page":0},{"id":118,"width":32,"height":32,"xoffset":0,"yoffset":-22.26,"xadvance":21.336000000000002,"chnl":15,"x":122,"y":478,"page":0},{"id":122,"width":28,"height":32,"xoffset":0,"yoffset":-22.26,"xadvance":19.068,"chnl":15,"x":156,"y":478,"page":0},{"id":58,"width":19,"height":32,"xoffset":0,"yoffset":-21.252000000000002,"xadvance":10.08,"chnl":15,"x":186,"y":478,"page":0},{"id":61,"width":29,"height":31,"xoffset":0,"yoffset":-20.580000000000002,"xadvance":21.588,"chnl":15,"x":207,"y":478,"page":0},{"id":95,"width":31,"height":17,"xoffset":0,"yoffset":0,"xadvance":21.84,"chnl":15,"x":238,"y":478,"page":0},{"id":126,"width":30,"height":27,"xoffset":0,"yoffset":-16.968,"xadvance":21.336000000000002,"chnl":15,"x":99,"y":163,"page":0},{"id":45,"width":25,"height":25,"xoffset":0,"yoffset":-15.498000000000001,"xadvance":17.052,"chnl":15,"x":485,"y":217,"page":0},{"id":44,"width":19,"height":24,"xoffset":0,"yoffset":-6.510000000000001,"xadvance":10.08,"chnl":15,"x":131,"y":163,"page":0},{"id":46,"width":19,"height":17,"xoffset":0,"yoffset":-6.510000000000001,"xadvance":10.08,"chnl":15,"x":271,"y":478,"page":0},{"id":32,"width":0,"height":0,"xoffset":0,"yoffset":0,"xadvance":10.248000000000001,"chnl":15,"x":238,"y":497,"page":0}],"info":{"face":"Fira Sans SemiBold","size":42,"bold":0,"italic":0,"charset":[" ","!","\"","#","$","%","&","'","(",")","*","+",",","-",".","/","0","1","2","3","4","5","6","7","8","9",":",";","<","=",">","?","@","A","B","C","D","E","F","G","H","I","J","K","L","M","N","O","P","Q","R","S","T","U","V","W","X","Y","Z","[","\\","]","^","_","`","a","b","c","d","e","f","g","h","i","j","k","l","m","n","o","p","q","r","s","t","u","v","w","x","y","z","{","|","}","~"],"unicode":1,"stretchH":100,"smooth":1,"aa":1,"padding":[0,0,0,0],"spacing":[2,2]},"common":{"lineHeight":50.400000000000006,"base":39.27,"scaleW":512,"scaleH":512,"pages":1,"packed":0,"alphaChnl":0,"redChnl":0,"greenChnl":0,"blueChnl":0},"kernings":[]}
