{"pages":["LibreBarcode39ExtendedText-Regular.png","LibreBarcode39ExtendedText-Regularpng"],"chars":[{"id":96,"width":54,"height":40,"xoffset":0,"yoffset":-24.78,"xadvance":45.36,"chnl":15,"x":0,"y":0,"page":0},{"id":126,"width":54,"height":44,"xoffset":0,"yoffset":-24.78,"xadvance":45.36,"chnl":15,"x":0,"y":42,"page":0},{"id":35,"width":54,"height":48,"xoffset":0,"yoffset":-24.78,"xadvance":45.36,"chnl":15,"x":0,"y":88,"page":0},{"id":36,"width":54,"height":49,"xoffset":0,"yoffset":-24.78,"xadvance":45.36,"chnl":15,"x":0,"y":138,"page":0},{"id":37,"width":54,"height":48,"xoffset":0,"yoffset":-24.78,"xadvance":45.36,"chnl":15,"x":0,"y":189,"page":0},{"id":38,"width":54,"height":48,"xoffset":0,"yoffset":-24.78,"xadvance":45.36,"chnl":15,"x":0,"y":239,"page":0},{"id":39,"width":54,"height":42,"xoffset":0,"yoffset":-24.78,"xadvance":45.36,"chnl":15,"x":0,"y":289,"page":0},{"id":40,"width":54,"height":51,"xoffset":0,"yoffset":-24.78,"xadvance":45.36,"chnl":15,"x":0,"y":333,"page":0},{"id":41,"width":54,"height":51,"xoffset":0,"yoffset":-24.78,"xadvance":45.36,"chnl":15,"x":0,"y":386,"page":0},{"id":125,"width":54,"height":51,"xoffset":0,"yoffset":-24.78,"xadvance":45.36,"chnl":15,"x":0,"y":439,"page":0},{"id":43,"width":54,"height":47,"xoffset":0,"yoffset":-24.78,"xadvance":45.36,"chnl":15,"x":56,"y":439,"page":0},{"id":44,"width":54,"height":51,"xoffset":0,"yoffset":-24.78,"xadvance":45.36,"chnl":15,"x":56,"y":386,"page":0},{"id":124,"width":54,"height":51,"xoffset":0,"yoffset":-24.78,"xadvance":45.36,"chnl":15,"x":112,"y":386,"page":0},{"id":47,"width":54,"height":49,"xoffset":0,"yoffset":-24.78,"xadvance":45.36,"chnl":15,"x":168,"y":386,"page":0},{"id":58,"width":54,"height":48,"xoffset":0,"yoffset":-24.78,"xadvance":45.36,"chnl":15,"x":224,"y":386,"page":0},{"id":59,"width":54,"height":51,"xoffset":0,"yoffset":-24.78,"xadvance":45.36,"chnl":15,"x":56,"y":333,"page":0},{"id":60,"width":54,"height":47,"xoffset":0,"yoffset":-24.78,"xadvance":45.36,"chnl":15,"x":112,"y":439,"page":0},{"id":61,"width":54,"height":45,"xoffset":0,"yoffset":-24.78,"xadvance":45.36,"chnl":15,"x":168,"y":439,"page":0},{"id":62,"width":54,"height":47,"xoffset":0,"yoffset":-24.78,"xadvance":45.36,"chnl":15,"x":280,"y":386,"page":0},{"id":63,"width":54,"height":48,"xoffset":0,"yoffset":-24.78,"xadvance":45.36,"chnl":15,"x":112,"y":333,"page":0},{"id":64,"width":54,"height":48,"xoffset":0,"yoffset":-24.78,"xadvance":45.36,"chnl":15,"x":168,"y":333,"page":0},{"id":33,"width":54,"height":48,"xoffset":0,"yoffset":-24.78,"xadvance":45.36,"chnl":15,"x":224,"y":333,"page":0},{"id":122,"width":54,"height":48,"xoffset":0,"yoffset":-24.78,"xadvance":45.36,"chnl":15,"x":280,"y":333,"page":0},{"id":92,"width":54,"height":49,"xoffset":0,"yoffset":-24.78,"xadvance":45.36,"chnl":15,"x":56,"y":138,"page":0},{"id":94,"width":54,"height":43,"xoffset":0,"yoffset":-24.78,"xadvance":45.36,"chnl":15,"x":224,"y":439,"page":0},{"id":95,"width":54,"height":49,"xoffset":0,"yoffset":-24.78,"xadvance":45.36,"chnl":15,"x":112,"y":138,"page":0},{"id":34,"width":54,"height":42,"xoffset":0,"yoffset":-24.78,"xadvance":45.36,"chnl":15,"x":280,"y":439,"page":0},{"id":97,"width":54,"height":48,"xoffset":0,"yoffset":-24.78,"xadvance":45.36,"chnl":15,"x":336,"y":333,"page":0},{"id":98,"width":54,"height":48,"xoffset":0,"yoffset":-24.78,"xadvance":45.36,"chnl":15,"x":392,"y":333,"page":0},{"id":99,"width":54,"height":48,"xoffset":0,"yoffset":-24.78,"xadvance":45.36,"chnl":15,"x":448,"y":333,"page":0},{"id":100,"width":54,"height":48,"xoffset":0,"yoffset":-24.78,"xadvance":45.36,"chnl":15,"x":56,"y":239,"page":0},{"id":101,"width":54,"height":48,"xoffset":0,"yoffset":-24.78,"xadvance":45.36,"chnl":15,"x":112,"y":239,"page":0},{"id":102,"width":54,"height":48,"xoffset":0,"yoffset":-24.78,"xadvance":45.36,"chnl":15,"x":168,"y":239,"page":0},{"id":104,"width":54,"height":48,"xoffset":0,"yoffset":-24.78,"xadvance":45.36,"chnl":15,"x":224,"y":239,"page":0},{"id":105,"width":54,"height":48,"xoffset":0,"yoffset":-24.78,"xadvance":45.36,"chnl":15,"x":280,"y":239,"page":0},{"id":107,"width":54,"height":48,"xoffset":0,"yoffset":-24.78,"xadvance":45.36,"chnl":15,"x":336,"y":239,"page":0},{"id":108,"width":54,"height":48,"xoffset":0,"yoffset":-24.78,"xadvance":45.36,"chnl":15,"x":392,"y":239,"page":0},{"id":109,"width":54,"height":48,"xoffset":0,"yoffset":-24.78,"xadvance":45.36,"chnl":15,"x":448,"y":239,"page":0},{"id":110,"width":54,"height":48,"xoffset":0,"yoffset":-24.78,"xadvance":45.36,"chnl":15,"x":56,"y":189,"page":0},{"id":111,"width":54,"height":48,"xoffset":0,"yoffset":-24.78,"xadvance":45.36,"chnl":15,"x":112,"y":189,"page":0},{"id":114,"width":54,"height":48,"xoffset":0,"yoffset":-24.78,"xadvance":45.36,"chnl":15,"x":168,"y":189,"page":0},{"id":115,"width":54,"height":48,"xoffset":0,"yoffset":-24.78,"xadvance":45.36,"chnl":15,"x":224,"y":189,"page":0},{"id":116,"width":54,"height":48,"xoffset":0,"yoffset":-24.78,"xadvance":45.36,"chnl":15,"x":280,"y":189,"page":0},{"id":117,"width":54,"height":48,"xoffset":0,"yoffset":-24.78,"xadvance":45.36,"chnl":15,"x":336,"y":189,"page":0},{"id":118,"width":54,"height":48,"xoffset":0,"yoffset":-24.78,"xadvance":45.36,"chnl":15,"x":392,"y":189,"page":0},{"id":119,"width":54,"height":48,"xoffset":0,"yoffset":-24.78,"xadvance":45.36,"chnl":15,"x":448,"y":189,"page":0},{"id":120,"width":54,"height":48,"xoffset":0,"yoffset":-24.78,"xadvance":45.36,"chnl":15,"x":168,"y":138,"page":0},{"id":88,"width":30,"height":48,"xoffset":0,"yoffset":-24.78,"xadvance":21.42,"chnl":15,"x":224,"y":138,"page":0},{"id":89,"width":30,"height":48,"xoffset":0,"yoffset":-24.78,"xadvance":21.42,"chnl":15,"x":256,"y":138,"page":0},{"id":90,"width":30,"height":48,"xoffset":0,"yoffset":-24.78,"xadvance":21.42,"chnl":15,"x":288,"y":138,"page":0},{"id":55,"width":30,"height":48,"xoffset":0,"yoffset":-24.78,"xadvance":21.42,"chnl":15,"x":320,"y":138,"page":0},{"id":56,"width":30,"height":48,"xoffset":0,"yoffset":-24.78,"xadvance":21.42,"chnl":15,"x":352,"y":138,"page":0},{"id":57,"width":30,"height":48,"xoffset":0,"yoffset":-24.78,"xadvance":21.42,"chnl":15,"x":384,"y":138,"page":0},{"id":46,"width":30,"height":48,"xoffset":0,"yoffset":-24.78,"xadvance":21.42,"chnl":15,"x":416,"y":138,"page":0},{"id":79,"width":30,"height":48,"xoffset":0,"yoffset":-24.78,"xadvance":21.42,"chnl":15,"x":448,"y":138,"page":0},{"id":48,"width":30,"height":48,"xoffset":0,"yoffset":-24.78,"xadvance":21.42,"chnl":15,"x":480,"y":138,"page":0},{"id":49,"width":30,"height":48,"xoffset":0,"yoffset":-24.78,"xadvance":21.42,"chnl":15,"x":56,"y":88,"page":0},{"id":50,"width":30,"height":48,"xoffset":0,"yoffset":-24.78,"xadvance":21.42,"chnl":15,"x":88,"y":88,"page":0},{"id":51,"width":30,"height":48,"xoffset":0,"yoffset":-24.78,"xadvance":21.42,"chnl":15,"x":120,"y":88,"page":0},{"id":52,"width":30,"height":48,"xoffset":0,"yoffset":-24.78,"xadvance":21.42,"chnl":15,"x":152,"y":88,"page":0},{"id":65,"width":30,"height":48,"xoffset":0,"yoffset":-24.78,"xadvance":21.42,"chnl":15,"x":184,"y":88,"page":0},{"id":66,"width":30,"height":48,"xoffset":0,"yoffset":-24.78,"xadvance":21.42,"chnl":15,"x":216,"y":88,"page":0},{"id":67,"width":30,"height":48,"xoffset":0,"yoffset":-24.78,"xadvance":21.42,"chnl":15,"x":248,"y":88,"page":0},{"id":68,"width":30,"height":48,"xoffset":0,"yoffset":-24.78,"xadvance":21.42,"chnl":15,"x":280,"y":88,"page":0},{"id":69,"width":30,"height":48,"xoffset":0,"yoffset":-24.78,"xadvance":21.42,"chnl":15,"x":312,"y":88,"page":0},{"id":70,"width":30,"height":48,"xoffset":0,"yoffset":-24.78,"xadvance":21.42,"chnl":15,"x":344,"y":88,"page":0},{"id":71,"width":30,"height":48,"xoffset":0,"yoffset":-24.78,"xadvance":21.42,"chnl":15,"x":376,"y":88,"page":0},{"id":72,"width":30,"height":48,"xoffset":0,"yoffset":-24.78,"xadvance":21.42,"chnl":15,"x":408,"y":88,"page":0},{"id":73,"width":30,"height":48,"xoffset":0,"yoffset":-24.78,"xadvance":21.42,"chnl":15,"x":440,"y":88,"page":0},{"id":74,"width":30,"height":48,"xoffset":0,"yoffset":-24.78,"xadvance":21.42,"chnl":15,"x":472,"y":88,"page":0},{"id":45,"width":30,"height":44,"xoffset":0,"yoffset":-24.78,"xadvance":21.42,"chnl":15,"x":336,"y":386,"page":0},{"id":42,"width":30,"height":35,"xoffset":0,"yoffset":-24.78,"xadvance":21.42,"chnl":15,"x":336,"y":439,"page":0},{"id":32,"width":30,"height":35,"xoffset":0,"yoffset":-24.78,"xadvance":21.42,"chnl":15,"x":368,"y":439,"page":0},{"id":91,"width":54,"height":50,"xoffset":0,"yoffset":-24.78,"xadvance":45.36,"chnl":15,"x":0,"y":0,"page":1},{"id":93,"width":54,"height":50,"xoffset":0,"yoffset":-24.78,"xadvance":45.36,"chnl":15,"x":0,"y":52,"page":1},{"id":103,"width":54,"height":51,"xoffset":0,"yoffset":-24.78,"xadvance":45.36,"chnl":15,"x":0,"y":104,"page":1},{"id":106,"width":54,"height":51,"xoffset":0,"yoffset":-24.78,"xadvance":45.36,"chnl":15,"x":0,"y":157,"page":1},{"id":112,"width":54,"height":51,"xoffset":0,"yoffset":-24.78,"xadvance":45.36,"chnl":15,"x":0,"y":210,"page":1},{"id":113,"width":54,"height":51,"xoffset":0,"yoffset":-24.78,"xadvance":45.36,"chnl":15,"x":0,"y":263,"page":1},{"id":121,"width":54,"height":51,"xoffset":0,"yoffset":-24.78,"xadvance":45.36,"chnl":15,"x":0,"y":316,"page":1},{"id":123,"width":54,"height":51,"xoffset":0,"yoffset":-24.78,"xadvance":45.36,"chnl":15,"x":0,"y":369,"page":1},{"id":81,"width":30,"height":50,"xoffset":0,"yoffset":-24.78,"xadvance":21.42,"chnl":15,"x":0,"y":422,"page":1},{"id":75,"width":30,"height":48,"xoffset":0,"yoffset":-24.78,"xadvance":21.42,"chnl":15,"x":32,"y":422,"page":1},{"id":76,"width":30,"height":48,"xoffset":0,"yoffset":-24.78,"xadvance":21.42,"chnl":15,"x":64,"y":422,"page":1},{"id":77,"width":30,"height":48,"xoffset":0,"yoffset":-24.78,"xadvance":21.42,"chnl":15,"x":96,"y":422,"page":1},{"id":78,"width":30,"height":48,"xoffset":0,"yoffset":-24.78,"xadvance":21.42,"chnl":15,"x":128,"y":422,"page":1},{"id":53,"width":30,"height":48,"xoffset":0,"yoffset":-24.78,"xadvance":21.42,"chnl":15,"x":160,"y":422,"page":1},{"id":80,"width":30,"height":48,"xoffset":0,"yoffset":-24.78,"xadvance":21.42,"chnl":15,"x":192,"y":422,"page":1},{"id":54,"width":30,"height":48,"xoffset":0,"yoffset":-24.78,"xadvance":21.42,"chnl":15,"x":224,"y":422,"page":1},{"id":82,"width":30,"height":48,"xoffset":0,"yoffset":-24.78,"xadvance":21.42,"chnl":15,"x":256,"y":422,"page":1},{"id":83,"width":30,"height":48,"xoffset":0,"yoffset":-24.78,"xadvance":21.42,"chnl":15,"x":288,"y":422,"page":1},{"id":84,"width":30,"height":48,"xoffset":0,"yoffset":-24.78,"xadvance":21.42,"chnl":15,"x":320,"y":422,"page":1},{"id":85,"width":30,"height":48,"xoffset":0,"yoffset":-24.78,"xadvance":21.42,"chnl":15,"x":352,"y":422,"page":1},{"id":86,"width":30,"height":48,"xoffset":0,"yoffset":-24.78,"xadvance":21.42,"chnl":15,"x":384,"y":422,"page":1},{"id":87,"width":30,"height":48,"xoffset":0,"yoffset":-24.78,"xadvance":21.42,"chnl":15,"x":416,"y":422,"page":1}],"info":{"face":"Libre Barcode 39 Extended Text Regular","size":42,"bold":0,"italic":0,"charset":[" ","!","\"","#","$","%","&","'","(",")","*","+",",","-",".","/","0","1","2","3","4","5","6","7","8","9",":",";","<","=",">","?","@","A","B","C","D","E","F","G","H","I","J","K","L","M","N","O","P","Q","R","S","T","U","V","W","X","Y","Z","[","\\","]","^","_","`","a","b","c","d","e","f","g","h","i","j","k","l","m","n","o","p","q","r","s","t","u","v","w","x","y","z","{","|","}","~"],"unicode":1,"stretchH":100,"smooth":1,"aa":1,"padding":[0,0,0,0],"spacing":[2,2]},"common":{"lineHeight":42,"base":25.200000000000003,"scaleW":512,"scaleH":512,"pages":2,"packed":0,"alphaChnl":0,"redChnl":0,"greenChnl":0,"blueChnl":0},"kernings":[]}
