{"pages":["Rubik-MediumItalic.png"],"chars":[{"id":124,"width":24,"height":56,"xoffset":0,"yoffset":-37.632000000000005,"xadvance":10.458,"chnl":15,"x":0,"y":0,"page":0},{"id":123,"width":30,"height":49,"xoffset":0,"yoffset":-32.592,"xadvance":16.674,"chnl":15,"x":0,"y":58,"page":0},{"id":91,"width":29,"height":49,"xoffset":0,"yoffset":-32.592,"xadvance":14.868,"chnl":15,"x":0,"y":109,"page":0},{"id":40,"width":28,"height":49,"xoffset":0,"yoffset":-32.592,"xadvance":15.120000000000001,"chnl":15,"x":0,"y":160,"page":0},{"id":41,"width":27,"height":49,"xoffset":0,"yoffset":-32.592,"xadvance":15.120000000000001,"chnl":15,"x":0,"y":211,"page":0},{"id":125,"width":29,"height":49,"xoffset":0,"yoffset":-32.592,"xadvance":16.674,"chnl":15,"x":0,"y":262,"page":0},{"id":93,"width":29,"height":49,"xoffset":0,"yoffset":-32.592,"xadvance":14.826,"chnl":15,"x":0,"y":313,"page":0},{"id":36,"width":37,"height":48,"xoffset":0,"yoffset":-33.6,"xadvance":27.048000000000002,"chnl":15,"x":0,"y":364,"page":0},{"id":106,"width":29,"height":48,"xoffset":0,"yoffset":-30.492,"xadvance":11.718,"chnl":15,"x":0,"y":414,"page":0},{"id":47,"width":37,"height":47,"xoffset":0,"yoffset":-33.012,"xadvance":21.546000000000003,"chnl":15,"x":0,"y":464,"page":0},{"id":92,"width":27,"height":47,"xoffset":0,"yoffset":-33.012,"xadvance":21.084,"chnl":15,"x":39,"y":464,"page":0},{"id":109,"width":46,"height":32,"xoffset":0,"yoffset":-22.26,"xadvance":37.926,"chnl":15,"x":68,"y":464,"page":0},{"id":87,"width":46,"height":39,"xoffset":0,"yoffset":-29.400000000000002,"xadvance":33.936,"chnl":15,"x":31,"y":414,"page":0},{"id":119,"width":45,"height":32,"xoffset":0,"yoffset":-21.84,"xadvance":34.482,"chnl":15,"x":116,"y":464,"page":0},{"id":64,"width":44,"height":43,"xoffset":0,"yoffset":-28.14,"xadvance":35.196000000000005,"chnl":15,"x":39,"y":364,"page":0},{"id":77,"width":44,"height":39,"xoffset":0,"yoffset":-29.400000000000002,"xadvance":34.104,"chnl":15,"x":79,"y":414,"page":0},{"id":81,"width":39,"height":43,"xoffset":0,"yoffset":-29.82,"xadvance":29.19,"chnl":15,"x":85,"y":364,"page":0},{"id":37,"width":43,"height":40,"xoffset":0,"yoffset":-29.610000000000003,"xadvance":34.062000000000005,"chnl":15,"x":126,"y":364,"page":0},{"id":103,"width":36,"height":42,"xoffset":0,"yoffset":-22.26,"xadvance":25.788,"chnl":15,"x":31,"y":313,"page":0},{"id":88,"width":42,"height":39,"xoffset":0,"yoffset":-29.400000000000002,"xadvance":27.804000000000002,"chnl":15,"x":125,"y":414,"page":0},{"id":72,"width":41,"height":39,"xoffset":0,"yoffset":-29.400000000000002,"xadvance":30.618000000000002,"chnl":15,"x":169,"y":414,"page":0},{"id":94,"width":30,"height":41,"xoffset":0,"yoffset":-30.618000000000002,"xadvance":18.816000000000003,"chnl":15,"x":69,"y":313,"page":0},{"id":96,"width":21,"height":41,"xoffset":0,"yoffset":-31.122000000000003,"xadvance":10.668000000000001,"chnl":15,"x":101,"y":313,"page":0},{"id":102,"width":31,"height":41,"xoffset":0,"yoffset":-31.080000000000002,"xadvance":17.262,"chnl":15,"x":124,"y":313,"page":0},{"id":86,"width":41,"height":39,"xoffset":0,"yoffset":-29.400000000000002,"xadvance":28.308000000000003,"chnl":15,"x":212,"y":414,"page":0},{"id":108,"width":22,"height":40,"xoffset":0,"yoffset":-29.82,"xadvance":11.13,"chnl":15,"x":171,"y":364,"page":0},{"id":107,"width":34,"height":40,"xoffset":0,"yoffset":-29.82,"xadvance":23.184,"chnl":15,"x":195,"y":364,"page":0},{"id":39,"width":21,"height":40,"xoffset":0,"yoffset":-29.82,"xadvance":9.618,"chnl":15,"x":231,"y":364,"page":0},{"id":105,"width":22,"height":40,"xoffset":0,"yoffset":-30.492,"xadvance":11.088000000000001,"chnl":15,"x":254,"y":364,"page":0},{"id":104,"width":34,"height":40,"xoffset":0,"yoffset":-29.82,"xadvance":26.418000000000003,"chnl":15,"x":278,"y":364,"page":0},{"id":63,"width":35,"height":40,"xoffset":0,"yoffset":-29.82,"xadvance":23.688000000000002,"chnl":15,"x":314,"y":364,"page":0},{"id":79,"width":38,"height":40,"xoffset":0,"yoffset":-29.82,"xadvance":29.19,"chnl":15,"x":351,"y":364,"page":0},{"id":38,"width":39,"height":40,"xoffset":0,"yoffset":-29.82,"xadvance":30.156000000000002,"chnl":15,"x":391,"y":364,"page":0},{"id":42,"width":28,"height":40,"xoffset":0,"yoffset":-29.568,"xadvance":18.69,"chnl":15,"x":432,"y":364,"page":0},{"id":67,"width":39,"height":40,"xoffset":0,"yoffset":-29.82,"xadvance":28.686000000000003,"chnl":15,"x":462,"y":364,"page":0},{"id":100,"width":36,"height":40,"xoffset":0,"yoffset":-29.82,"xadvance":25.704,"chnl":15,"x":157,"y":313,"page":0},{"id":98,"width":34,"height":40,"xoffset":0,"yoffset":-29.82,"xadvance":25.746000000000002,"chnl":15,"x":195,"y":313,"page":0},{"id":48,"width":37,"height":40,"xoffset":0,"yoffset":-29.82,"xadvance":27.552000000000003,"chnl":15,"x":231,"y":313,"page":0},{"id":71,"width":40,"height":40,"xoffset":0,"yoffset":-29.82,"xadvance":29.400000000000002,"chnl":15,"x":270,"y":313,"page":0},{"id":113,"width":35,"height":40,"xoffset":0,"yoffset":-22.26,"xadvance":25.746000000000002,"chnl":15,"x":312,"y":313,"page":0},{"id":50,"width":36,"height":40,"xoffset":0,"yoffset":-29.904000000000003,"xadvance":25.998,"chnl":15,"x":349,"y":313,"page":0},{"id":74,"width":38,"height":40,"xoffset":0,"yoffset":-29.400000000000002,"xadvance":27.216,"chnl":15,"x":387,"y":313,"page":0},{"id":51,"width":37,"height":40,"xoffset":0,"yoffset":-29.400000000000002,"xadvance":26.46,"chnl":15,"x":427,"y":313,"page":0},{"id":112,"width":35,"height":40,"xoffset":0,"yoffset":-22.26,"xadvance":25.704,"chnl":15,"x":466,"y":313,"page":0},{"id":34,"width":29,"height":40,"xoffset":0,"yoffset":-29.82,"xadvance":17.304000000000002,"chnl":15,"x":31,"y":262,"page":0},{"id":78,"width":40,"height":39,"xoffset":0,"yoffset":-29.400000000000002,"xadvance":29.736,"chnl":15,"x":255,"y":414,"page":0},{"id":53,"width":36,"height":40,"xoffset":0,"yoffset":-29.400000000000002,"xadvance":25.998,"chnl":15,"x":62,"y":262,"page":0},{"id":89,"width":40,"height":39,"xoffset":0,"yoffset":-29.400000000000002,"xadvance":27.804000000000002,"chnl":15,"x":297,"y":414,"page":0},{"id":54,"width":35,"height":40,"xoffset":0,"yoffset":-29.400000000000002,"xadvance":26.334000000000003,"chnl":15,"x":100,"y":262,"page":0},{"id":116,"width":28,"height":40,"xoffset":0,"yoffset":-29.82,"xadvance":17.766000000000002,"chnl":15,"x":137,"y":262,"page":0},{"id":83,"width":37,"height":40,"xoffset":0,"yoffset":-29.82,"xadvance":26.922,"chnl":15,"x":167,"y":262,"page":0},{"id":56,"width":36,"height":40,"xoffset":0,"yoffset":-29.82,"xadvance":27.468,"chnl":15,"x":206,"y":262,"page":0},{"id":85,"width":40,"height":40,"xoffset":0,"yoffset":-29.400000000000002,"xadvance":29.946,"chnl":15,"x":244,"y":262,"page":0},{"id":57,"width":37,"height":40,"xoffset":0,"yoffset":-29.82,"xadvance":25.914,"chnl":15,"x":286,"y":262,"page":0},{"id":121,"width":35,"height":40,"xoffset":0,"yoffset":-21.84,"xadvance":24.360000000000003,"chnl":15,"x":325,"y":262,"page":0},{"id":84,"width":38,"height":39,"xoffset":0,"yoffset":-29.400000000000002,"xadvance":25.242,"chnl":15,"x":339,"y":414,"page":0},{"id":80,"width":38,"height":39,"xoffset":0,"yoffset":-29.400000000000002,"xadvance":27.720000000000002,"chnl":15,"x":379,"y":414,"page":0},{"id":90,"width":38,"height":39,"xoffset":0,"yoffset":-29.400000000000002,"xadvance":26.124000000000002,"chnl":15,"x":419,"y":414,"page":0},{"id":33,"width":22,"height":39,"xoffset":0,"yoffset":-29.400000000000002,"xadvance":11.256,"chnl":15,"x":459,"y":414,"page":0},{"id":76,"width":32,"height":39,"xoffset":0,"yoffset":-29.400000000000002,"xadvance":24.108,"chnl":15,"x":362,"y":262,"page":0},{"id":75,"width":38,"height":39,"xoffset":0,"yoffset":-29.400000000000002,"xadvance":26.166,"chnl":15,"x":396,"y":262,"page":0},{"id":73,"width":23,"height":39,"xoffset":0,"yoffset":-29.400000000000002,"xadvance":12.558000000000002,"chnl":15,"x":483,"y":414,"page":0},{"id":35,"width":39,"height":38,"xoffset":0,"yoffset":-27.51,"xadvance":29.022000000000002,"chnl":15,"x":436,"y":262,"page":0},{"id":70,"width":37,"height":39,"xoffset":0,"yoffset":-29.400000000000002,"xadvance":25.326,"chnl":15,"x":29,"y":211,"page":0},{"id":49,"width":30,"height":39,"xoffset":0,"yoffset":-29.400000000000002,"xadvance":19.278000000000002,"chnl":15,"x":68,"y":211,"page":0},{"id":69,"width":37,"height":39,"xoffset":0,"yoffset":-29.400000000000002,"xadvance":26.082,"chnl":15,"x":100,"y":211,"page":0},{"id":52,"width":36,"height":39,"xoffset":0,"yoffset":-29.400000000000002,"xadvance":27.636000000000003,"chnl":15,"x":139,"y":211,"page":0},{"id":68,"width":39,"height":39,"xoffset":0,"yoffset":-29.400000000000002,"xadvance":29.484,"chnl":15,"x":177,"y":211,"page":0},{"id":55,"width":36,"height":39,"xoffset":0,"yoffset":-29.400000000000002,"xadvance":22.806,"chnl":15,"x":218,"y":211,"page":0},{"id":66,"width":38,"height":39,"xoffset":0,"yoffset":-29.400000000000002,"xadvance":28.896,"chnl":15,"x":256,"y":211,"page":0},{"id":65,"width":38,"height":39,"xoffset":0,"yoffset":-29.400000000000002,"xadvance":29.274,"chnl":15,"x":296,"y":211,"page":0},{"id":82,"width":39,"height":39,"xoffset":0,"yoffset":-29.400000000000002,"xadvance":28.266000000000002,"chnl":15,"x":336,"y":211,"page":0},{"id":62,"width":31,"height":37,"xoffset":0,"yoffset":-27.174000000000003,"xadvance":21.168000000000003,"chnl":15,"x":477,"y":262,"page":0},{"id":95,"width":37,"height":15,"xoffset":0,"yoffset":-2.436,"xadvance":31.038,"chnl":15,"x":163,"y":464,"page":0},{"id":60,"width":32,"height":37,"xoffset":0,"yoffset":-27.174000000000003,"xadvance":21.168000000000003,"chnl":15,"x":377,"y":211,"page":0},{"id":120,"width":36,"height":32,"xoffset":0,"yoffset":-21.84,"xadvance":23.646,"chnl":15,"x":411,"y":211,"page":0},{"id":118,"width":35,"height":32,"xoffset":0,"yoffset":-21.84,"xadvance":24.066000000000003,"chnl":15,"x":449,"y":211,"page":0},{"id":117,"width":35,"height":32,"xoffset":0,"yoffset":-21.84,"xadvance":26.082,"chnl":15,"x":30,"y":160,"page":0},{"id":97,"width":34,"height":33,"xoffset":0,"yoffset":-22.26,"xadvance":25.452,"chnl":15,"x":31,"y":109,"page":0},{"id":59,"width":22,"height":34,"xoffset":0,"yoffset":-20.748,"xadvance":12.012,"chnl":15,"x":32,"y":58,"page":0},{"id":110,"width":34,"height":32,"xoffset":0,"yoffset":-22.26,"xadvance":26.208000000000002,"chnl":15,"x":67,"y":160,"page":0},{"id":43,"width":34,"height":34,"xoffset":0,"yoffset":-23.814,"xadvance":25.578000000000003,"chnl":15,"x":56,"y":58,"page":0},{"id":115,"width":32,"height":33,"xoffset":0,"yoffset":-22.26,"xadvance":22.344,"chnl":15,"x":67,"y":109,"page":0},{"id":99,"width":33,"height":33,"xoffset":0,"yoffset":-22.26,"xadvance":23.94,"chnl":15,"x":101,"y":109,"page":0},{"id":111,"width":33,"height":33,"xoffset":0,"yoffset":-22.26,"xadvance":24.822000000000003,"chnl":15,"x":136,"y":109,"page":0},{"id":101,"width":33,"height":33,"xoffset":0,"yoffset":-22.26,"xadvance":24.150000000000002,"chnl":15,"x":171,"y":109,"page":0},{"id":122,"width":33,"height":32,"xoffset":0,"yoffset":-21.84,"xadvance":22.218,"chnl":15,"x":103,"y":160,"page":0},{"id":61,"width":33,"height":30,"xoffset":0,"yoffset":-20.034000000000002,"xadvance":23.94,"chnl":15,"x":138,"y":160,"page":0},{"id":114,"width":29,"height":32,"xoffset":0,"yoffset":-21.84,"xadvance":17.598000000000003,"chnl":15,"x":206,"y":109,"page":0},{"id":126,"width":32,"height":26,"xoffset":0,"yoffset":-15.750000000000002,"xadvance":23.394000000000002,"chnl":15,"x":173,"y":160,"page":0},{"id":58,"width":20,"height":31,"xoffset":0,"yoffset":-20.748,"xadvance":11.55,"chnl":15,"x":486,"y":211,"page":0},{"id":45,"width":28,"height":25,"xoffset":0,"yoffset":-14.994000000000002,"xadvance":20.16,"chnl":15,"x":207,"y":160,"page":0},{"id":44,"width":19,"height":19,"xoffset":0,"yoffset":-6.216,"xadvance":11.298,"chnl":15,"x":237,"y":160,"page":0},{"id":46,"width":17,"height":16,"xoffset":0,"yoffset":-6.216,"xadvance":11.13,"chnl":15,"x":258,"y":160,"page":0},{"id":32,"width":0,"height":0,"xoffset":0,"yoffset":0,"xadvance":9.786000000000001,"chnl":15,"x":68,"y":498,"page":0}],"info":{"face":"Rubik Medium Italic","size":42,"bold":0,"italic":0,"charset":[" ","!","\"","#","$","%","&","'","(",")","*","+",",","-",".","/","0","1","2","3","4","5","6","7","8","9",":",";","<","=",">","?","@","A","B","C","D","E","F","G","H","I","J","K","L","M","N","O","P","Q","R","S","T","U","V","W","X","Y","Z","[","\\","]","^","_","`","a","b","c","d","e","f","g","h","i","j","k","l","m","n","o","p","q","r","s","t","u","v","w","x","y","z","{","|","}","~"],"unicode":1,"stretchH":100,"smooth":1,"aa":1,"padding":[0,0,0,0],"spacing":[2,2]},"common":{"lineHeight":49.77,"base":39.27,"scaleW":512,"scaleH":512,"pages":1,"packed":0,"alphaChnl":0,"redChnl":0,"greenChnl":0,"blueChnl":0},"kernings":[{"first":34,"second":44,"amount":-3.9480000000000004},{"first":34,"second":45,"amount":-1.764},{"first":34,"second":46,"amount":-3.9480000000000004},{"first":34,"second":47,"amount":-2.73},{"first":34,"second":52,"amount":-1.6800000000000002},{"first":39,"second":44,"amount":-3.9480000000000004},{"first":39,"second":45,"amount":-1.764},{"first":39,"second":46,"amount":-3.9480000000000004},{"first":39,"second":47,"amount":-2.73},{"first":39,"second":52,"amount":-1.6800000000000002},{"first":40,"second":40,"amount":-0.21000000000000002},{"first":40,"second":48,"amount":-0.882},{"first":40,"second":49,"amount":-0.9660000000000001},{"first":40,"second":52,"amount":-1.806},{"first":40,"second":53,"amount":-0.42000000000000004},{"first":40,"second":56,"amount":-0.798},{"first":41,"second":41,"amount":-0.168},{"first":43,"second":49,"amount":-1.344},{"first":44,"second":34,"amount":-4.284000000000001},{"first":44,"second":39,"amount":-4.284000000000001},{"first":44,"second":45,"amount":-1.848},{"first":44,"second":48,"amount":-0.504},{"first":44,"second":49,"amount":-2.7720000000000002},{"first":44,"second":52,"amount":-0.672},{"first":44,"second":53,"amount":-0.252},{"first":44,"second":56,"amount":-0.42000000000000004},{"first":45,"second":34,"amount":-2.436},{"first":45,"second":39,"amount":-2.436},{"first":45,"second":49,"amount":-1.6380000000000001},{"first":45,"second":53,"amount":-0.29400000000000004},{"first":46,"second":34,"amount":-4.284000000000001},{"first":46,"second":39,"amount":-4.284000000000001},{"first":46,"second":45,"amount":-1.848},{"first":46,"second":48,"amount":-0.504},{"first":46,"second":49,"amount":-2.7720000000000002},{"first":46,"second":52,"amount":-0.672},{"first":46,"second":53,"amount":-0.252},{"first":46,"second":56,"amount":-0.42000000000000004},{"first":47,"second":47,"amount":-8.904},{"first":47,"second":48,"amount":-0.7140000000000001},{"first":47,"second":49,"amount":-0.336},{"first":47,"second":52,"amount":-2.2680000000000002},{"first":47,"second":53,"amount":-0.378},{"first":47,"second":56,"amount":-0.756},{"first":48,"second":44,"amount":-0.42000000000000004},{"first":48,"second":46,"amount":-0.42000000000000004},{"first":52,"second":34,"amount":-0.9660000000000001},{"first":52,"second":39,"amount":-0.9660000000000001},{"first":52,"second":44,"amount":-0.29400000000000004},{"first":52,"second":46,"amount":-0.29400000000000004},{"first":56,"second":45,"amount":-0.252},{"first":58,"second":34,"amount":-0.462},{"first":58,"second":39,"amount":-0.462},{"first":59,"second":34,"amount":-0.462},{"first":59,"second":39,"amount":-0.462},{"first":91,"second":40,"amount":-0.168},{"first":91,"second":48,"amount":-0.7140000000000001},{"first":91,"second":49,"amount":-0.882},{"first":91,"second":52,"amount":-1.344},{"first":91,"second":53,"amount":-0.168},{"first":91,"second":56,"amount":-0.672},{"first":92,"second":34,"amount":-2.7720000000000002},{"first":92,"second":39,"amount":-2.7720000000000002}]}
